mkdocs_pdf2image/__init__.py
mkdocs_pdf2image/plugin.py
mkdocs_pdf2image_plugin-0.1.2.dist-info/METADATA
mkdocs_pdf2image_plugin-0.1.2.dist-info/WHEEL
mkdocs_pdf2image_plugin-0.1.2.dist-info/entry_points.txt
mkdocs_pdf2image_plugin-0.1.2.dist-info/RECORD
