Metadata-Version: 2.1
Name: mkdocs-pdf2image-plugin
Version: 0.1.2
Summary: An MkDocs plugin to convert the first page of a pdf to an image
Home-page: https://github.com/supcik/mkdocs-pdf2image-plugin
License: Apache-2
Keywords: mkdocs,python,markdown,wiki
Author: Jacques Supcik
Author-email: jacques.supcik@hefr.ch
Requires-Python: >=3.10,<4.0
Classifier: Development Status :: 5 - Production/Stable
Classifier: Intended Audience :: Developers
Classifier: Intended Audience :: Information Technology
Classifier: License :: Other/Proprietary License
Classifier: Programming Language :: Python :: 3
Classifier: Programming Language :: Python :: 3.10
Classifier: Programming Language :: Python :: 3.11
Provides-Extra: test
Requires-Dist: mkdocs (>=1.5.2,<2.0.0)
Requires-Dist: mkdocs-material (>=9.3.1,<10.0.0) ; extra == "test"
Requires-Dist: pdf2image (>=1.16.3,<2.0.0)
Project-URL: Repository, https://github.com/supcik/mkdocs-pdf2image-plugin
